{
  "version": "7",
  "dialect": "postgresql",
  "entries": [
    {
      "idx": 0,
      "version": "7",
      "when": 1750087614826,
      "tag": "0000_whole_chamber",
      "breakpoints": true
    },
    {
      "idx": 1,
      "version": "7",
      "when": 1750370064684,
      "tag": "0001_lethal_hex",
      "breakpoints": true
    },
    {
      "idx": 2,
      "version": "7",
      "when": 1750371400614,
      "tag": "0002_puzzling_leech",
      "breakpoints": true
    },
    {
      "idx": 3,
      "version": "7",
      "when": 1750670982802,
      "tag": "0003_great_doctor_octopus",
      "breakpoints": true
    },
    {
      "idx": 4,
      "version": "7",
      "when": 1750775792758,
      "tag": "0004_lowly_enchantress",
      "breakpoints": true
    }
  ]
}